django_mailersend/__init__.py
django_mailersend/backend.py
django_mailersend-0.2.0.dist-info/METADATA
django_mailersend-0.2.0.dist-info/WHEEL
django_mailersend-0.2.0.dist-info/licenses/LICENSE.md
django_mailersend-0.2.0.dist-info/RECORD
