Metadata-Version: 2.1
Name: django-mailersend
Version: 0.2.0
Summary: Django MailerSend makes it easier to send emails in Django apps using the MailerSend API.
Author-email: Digital Valley <techteam@digitalvalley.nl>
License-File: LICENSE.md
Classifier: Development Status :: 3 - Alpha
Classifier: Framework :: Django
Classifier: License :: OSI Approved :: MIT License
Classifier: Programming Language :: Python :: 3
Requires-Python: >=3.7
Requires-Dist: django
Requires-Dist: mailersend
